TcpipXieyiRumenjiaochengCYuyanBianchengWang/README.md
TcpipXieyiRumenjiaochengCYuyanBianchengWang/__init__.py
TcpipXieyiRumenjiaochengCYuyanBianchengWang/__main__.py
TcpipXieyiRumenjiaochengCYuyanBianchengWang/file.epub
TcpipXieyiRumenjiaochengCYuyanBianchengWang/index.html
TcpipXieyiRumenjiaochengCYuyanBianchengWang/css/__init__.py
TcpipXieyiRumenjiaochengCYuyanBianchengWang/css/annotations.css
TcpipXieyiRumenjiaochengCYuyanBianchengWang/css/main.css
TcpipXieyiRumenjiaochengCYuyanBianchengWang/css/normalize.css
TcpipXieyiRumenjiaochengCYuyanBianchengWang/css/popup.css
TcpipXieyiRumenjiaochengCYuyanBianchengWang/font/__init__.py
TcpipXieyiRumenjiaochengCYuyanBianchengWang/font/fontello.eot
TcpipXieyiRumenjiaochengCYuyanBianchengWang/font/fontello.svg
TcpipXieyiRumenjiaochengCYuyanBianchengWang/font/fontello.ttf
TcpipXieyiRumenjiaochengCYuyanBianchengWang/font/fontello.woff
TcpipXieyiRumenjiaochengCYuyanBianchengWang/img/__init__.py
TcpipXieyiRumenjiaochengCYuyanBianchengWang/img/annotator-glyph-sprite.png
TcpipXieyiRumenjiaochengCYuyanBianchengWang/img/annotator-icon-sprite.png
TcpipXieyiRumenjiaochengCYuyanBianchengWang/img/apple-touch-icon.png
TcpipXieyiRumenjiaochengCYuyanBianchengWang/img/cancelfullscreen.png
TcpipXieyiRumenjiaochengCYuyanBianchengWang/img/close.png
TcpipXieyiRumenjiaochengCYuyanBianchengWang/img/fullscreen.png
TcpipXieyiRumenjiaochengCYuyanBianchengWang/img/loader.gif
TcpipXieyiRumenjiaochengCYuyanBianchengWang/img/menu-icon.png
TcpipXieyiRumenjiaochengCYuyanBianchengWang/img/save.png
TcpipXieyiRumenjiaochengCYuyanBianchengWang/img/saved.png
TcpipXieyiRumenjiaochengCYuyanBianchengWang/img/settings-s.png
TcpipXieyiRumenjiaochengCYuyanBianchengWang/img/settings.png
TcpipXieyiRumenjiaochengCYuyanBianchengWang/img/star.png
TcpipXieyiRumenjiaochengCYuyanBianchengWang/js/__init__.py
TcpipXieyiRumenjiaochengCYuyanBianchengWang/js/epub.js
TcpipXieyiRumenjiaochengCYuyanBianchengWang/js/epub.min.js
tcpip_xieyi_rumenjiaocheng_c_yuyan_biancheng_wang-2024.3.5.0.dist-info/METADATA
tcpip_xieyi_rumenjiaocheng_c_yuyan_biancheng_wang-2024.3.5.0.dist-info/WHEEL
tcpip_xieyi_rumenjiaocheng_c_yuyan_biancheng_wang-2024.3.5.0.dist-info/entry_points.txt
tcpip_xieyi_rumenjiaocheng_c_yuyan_biancheng_wang-2024.3.5.0.dist-info/top_level.txt
tcpip_xieyi_rumenjiaocheng_c_yuyan_biancheng_wang-2024.3.5.0.dist-info/RECORD
